odoo/addons/l10n_hr_city/README.rst
odoo/addons/l10n_hr_city/__init__.py
odoo/addons/l10n_hr_city/__manifest__.py
odoo/addons/l10n_hr_city/data/res.city.csv
odoo/addons/l10n_hr_city/data/res_country_state_data.xml
odoo/addons/l10n_hr_city/doc/changelog.rst
odoo/addons/l10n_hr_city/doc/index.rst
odoo/addons/l10n_hr_city/i18n/l10n_hr_city.pot
odoo/addons/l10n_hr_city/static/description/icon.png
odoo_addon_l10n_hr_city-16.0.1.0.1.dist-info/METADATA
odoo_addon_l10n_hr_city-16.0.1.0.1.dist-info/WHEEL
odoo_addon_l10n_hr_city-16.0.1.0.1.dist-info/top_level.txt
odoo_addon_l10n_hr_city-16.0.1.0.1.dist-info/RECORD
